dataworkspaces/__init__.py
dataworkspaces/__main__.py
dataworkspaces/api.py
dataworkspaces/dws.py
dataworkspaces/errors.py
dataworkspaces/lineage.py
dataworkspaces/workspace.py
dataworkspaces/backends/__init__.py
dataworkspaces/backends/git.py
dataworkspaces/commands/__init__.py
dataworkspaces/commands/add.py
dataworkspaces/commands/clone.py
dataworkspaces/commands/config.py
dataworkspaces/commands/delete_snapshot.py
dataworkspaces/commands/deploy.py
dataworkspaces/commands/diff.py
dataworkspaces/commands/init.py
dataworkspaces/commands/lineage.py
dataworkspaces/commands/publish.py
dataworkspaces/commands/pull.py
dataworkspaces/commands/push.py
dataworkspaces/commands/report.py
dataworkspaces/commands/restore.py
dataworkspaces/commands/run.py
dataworkspaces/commands/snapshot.py
dataworkspaces/commands/status.py
dataworkspaces/kits/__init__.py
dataworkspaces/kits/jupyter.py
dataworkspaces/kits/scikit_learn.py
dataworkspaces/kits/tensorflow.py
dataworkspaces/kits/wrapper_utils.py
dataworkspaces/resources/__init__.py
dataworkspaces/resources/api_resource.py
dataworkspaces/resources/git_resource.py
dataworkspaces/resources/hashtree.py
dataworkspaces/resources/local_file_resource.py
dataworkspaces/resources/rclone_resource.py
dataworkspaces/resources/resource_types.py
dataworkspaces/resources/s3/__init__.py
dataworkspaces/resources/s3/s3_resource.py
dataworkspaces/resources/s3/snapfs.py
dataworkspaces/resources/s3/snapshot.py
dataworkspaces/third_party/__init__.py
dataworkspaces/third_party/git-fat
dataworkspaces/third_party/git_fat.py
dataworkspaces/third_party/lineage_graph_template.html
dataworkspaces/third_party/rclone.py
dataworkspaces/utils/__init__.py
dataworkspaces/utils/file_utils.py
dataworkspaces/utils/git_fat_utils.py
dataworkspaces/utils/git_lfs_utils.py
dataworkspaces/utils/git_utils.py
dataworkspaces/utils/hash_utils.py
dataworkspaces/utils/lineage_utils.py
dataworkspaces/utils/param_utils.py
dataworkspaces/utils/print_utils.py
dataworkspaces-1.6.0.dist-info/LICENSE.txt
dataworkspaces-1.6.0.dist-info/METADATA
dataworkspaces-1.6.0.dist-info/WHEEL
dataworkspaces-1.6.0.dist-info/entry_points.txt
dataworkspaces-1.6.0.dist-info/top_level.txt
dataworkspaces-1.6.0.dist-info/RECORD
