Metadata-Version: 2.1
Name: dataworkspaces
Version: 1.6.0
Summary: Easy management of source data, intermediate data, and results for data science projects
Home-page: https://github.com/data-workspaces/data-workspaces-core
Author: Max Plack Institute for Software Systems, Benedat LLC
Author-email: jeff.fischer@benedat.com
License: UNKNOWN
Platform: UNKNOWN
Classifier: Programming Language :: Python :: 3 :: Only
Classifier: Development Status :: 4 - Beta
Classifier: License :: OSI Approved :: Apache Software License
Classifier: Operating System :: MacOS
Classifier: Operating System :: POSIX :: Linux
Classifier: Operating System :: POSIX
Classifier: Operating System :: Microsoft :: Windows :: Windows 10
Classifier: Topic :: Software Development :: Version Control
Classifier: Topic :: Scientific/Engineering :: Information Analysis
Requires-Python: >=3.7
License-File: LICENSE.txt
Requires-Dist: click
Requires-Dist: requests
Provides-Extra: docker
Requires-Dist: chardet ; extra == 'docker'
Requires-Dist: dws-repo2docker ; extra == 'docker'
Provides-Extra: s3
Requires-Dist: boto3 ; extra == 's3'
Requires-Dist: s3fs ; extra == 's3'
